{
  "date": "2026-01-31",
  "version": "V9.0",
  "dossier": [
    {
      "symbol": "AAPL",
      "action": "DISCARD",
      "reasoning_score": 0,
      "risk_level": "LOW",
      "thesis": {
        "summary": "분석할 뉴스 내용이 없습니다."
      },
      "last_updated": "17:36"
    },
    {
      "symbol": "MSFT",
      "action": "DISCARD",
      "reasoning_score": 0,
      "risk_level": "LOW",
      "thesis": {
        "summary": "분석할 뉴스 내용이 없습니다."
      },
      "last_updated": "17:36"
    },
    {
      "symbol": "GOOGL",
      "action": "DISCARD",
      "reasoning_score": 0,
      "risk_level": "LOW",
      "thesis": {
        "summary": "분석할 뉴스 내용이 없습니다."
      },
      "last_updated": "17:36"
    },
    {
      "symbol": "AMZN",
      "action": "DISCARD",
      "reasoning_score": 0,
      "risk_level": "LOW",
      "thesis": {
        "summary": "분석할 뉴스 내용이 없습니다."
      },
      "last_updated": "17:36"
    },
    {
      "symbol": "NVDA",
      "action": "DISCARD",
      "reasoning_score": 0,
      "risk_level": "LOW",
      "thesis": {
        "summary": "분석할 뉴스 내용이 없습니다."
      },
      "last_updated": "17:36"
    },
    {
      "symbol": "TSLA",
      "action": "DISCARD",
      "reasoning_score": 0,
      "risk_level": "LOW",
      "thesis": {
        "summary": "분석할 뉴스 내용이 없습니다."
      },
      "last_updated": "17:36"
    },
    {
      "symbol": "META",
      "action": "DISCARD",
      "reasoning_score": 0,
      "risk_level": "LOW",
      "thesis": {
        "summary": "분석할 뉴스의 내용이 없습니다."
      },
      "last_updated": "17:36"
    },
    {
      "symbol": "BRK-B",
      "action": "DISCARD",
      "reasoning_score": 0,
      "risk_level": "LOW",
      "thesis": {
        "summary": "분석할 뉴스 내용이 제공되지 않았습니다."
      },
      "last_updated": "17:37"
    },
    {
      "symbol": "V",
      "action": "DISCARD",
      "reasoning_score": 0,
      "risk_level": "LOW",
      "thesis": {
        "summary": "분석할 뉴스 내용이 없습니다."
      },
      "last_updated": "17:37"
    },
    {
      "symbol": "UNH",
      "action": "DISCARD",
      "reasoning_score": 0,
      "risk_level": "LOW",
      "thesis": {
        "summary": "분석할 뉴스 내용이 없습니다."
      },
      "last_updated": "17:37"
    },
    {
      "symbol": "XOM",
      "action": "DISCARD",
      "reasoning_score": 0,
      "risk_level": "LOW",
      "thesis": {
        "summary": "분석할 뉴스 내용이 없습니다."
      },
      "last_updated": "17:37"
    },
    {
      "symbol": "JNJ",
      "action": "DISCARD",
      "reasoning_score": 0,
      "risk_level": "LOW",
      "thesis": {
        "summary": "분석할 뉴스 내용이 없습니다."
      },
      "last_updated": "17:37"
    },
    {
      "symbol": "JPM",
      "action": "DISCARD",
      "reasoning_score": 0,
      "risk_level": "LOW",
      "thesis": {
        "summary": "분석할 뉴스 내용이 없습니다."
      },
      "last_updated": "17:37"
    },
    {
      "symbol": "WMT",
      "action": "DISCARD",
      "reasoning_score": 0,
      "risk_level": "LOW",
      "thesis": {
        "summary": "분석할 뉴스 내용이 없습니다."
      },
      "last_updated": "17:37"
    },
    {
      "symbol": "PG",
      "action": "DISCARD",
      "reasoning_score": 0,
      "risk_level": "LOW",
      "thesis": {
        "summary": "분석할 뉴스 내용이 없습니다."
      },
      "last_updated": "17:37"
    },
    {
      "symbol": "MA",
      "action": "DISCARD",
      "reasoning_score": 0,
      "risk_level": "LOW",
      "thesis": {
        "summary": "분석할 뉴스 내용이 없습니다."
      },
      "last_updated": "17:38"
    },
    {
      "symbol": "LLY",
      "action": "DISCARD",
      "reasoning_score": 0,
      "risk_level": "LOW",
      "thesis": {
        "summary": "분석할 뉴스 내용이 없습니다."
      },
      "last_updated": "17:38"
    },
    {
      "symbol": "CVX",
      "action": "DISCARD",
      "reasoning_score": 0,
      "risk_level": "LOW",
      "thesis": {
        "summary": "분석할 뉴스 내용이 없습니다."
      },
      "last_updated": "17:38"
    },
    {
      "symbol": "HD",
      "action": "DISCARD",
      "reasoning_score": 0,
      "risk_level": "LOW",
      "thesis": {
        "summary": "분석할 뉴스 내용이 없습니다."
      },
      "last_updated": "17:38"
    },
    {
      "symbol": "MRK",
      "action": "DISCARD",
      "reasoning_score": 0,
      "risk_level": "LOW",
      "thesis": {
        "summary": "분석할 뉴스 내용이 없습니다."
      },
      "last_updated": "17:38"
    }
  ]
}